{
      "predicate":"has_anatomical_site",
      "display_name":"Anatomical Site",
      "abstractor_object_type":"list",
      "preferred_name":"anatomical site",
      "predicate_variants":[

      ],
      "object_values":[
         {
            "value":"colon",
            "properties":{
              "tui":"T023"
            },
            "vocabulary_code":"71854001",
            "vocabulary":"SNOMED-CT",
            "vocabulary_version":"2016_03_01",
            "object_value_variants":[
            ]
         },
         {
            "value":"proximal colon",
            "properties":{
              "tui":"T023"
            },
            "vocabulary_code":"51342009",
            "vocabulary":"SNOMED-CT",
            "vocabulary_version":"2016_03_01",
            "object_value_variants":[
               {
                  "value":"right colon"
               },
              {
                "value":"right-sided"
              }
            ]
         },
         {
            "value":"distal colon",
            "properties":{
              "tui":"T023"
            },
            "vocabulary_code":"55572008",
            "vocabulary":"SNOMED-CT",
            "vocabulary_version":"2016_03_01",
            "object_value_variants":[
               {
                  "value":"left colon"
               },
              {
                "value":"left-sided"
              }
            ]
         },
         {
            "value":"rectum",
            "properties":{
              "tui":"T023"
            },
            "vocabulary_code":"34402009",
            "vocabulary":"SNOMED-CT",
            "vocabulary_version":"2016_03_01",
            "object_value_variants":[
               {
                  "value":"rectal"
               },
              {
                "value":"anus"
              }
            ]
         },
        {
          "value":"rectosigmoid colon",
          "properties":{
            "tui":"T023"
          },
          "vocabulary_code":"81922002",
          "vocabulary":"SNOMED-CT",
          "vocabulary_version":"2016_03_01",
          "object_value_variants":[
            {
              "value":"rectosigmoid"
            }
          ]
        },
        {
          "value":"sigmoid colon",
          "properties":{
            "tui":"T023"
          },
          "vocabulary_code":"60184004",
          "vocabulary":"SNOMED-CT",
          "vocabulary_version":"2016_03_01",
          "object_value_variants":[
            {
              "value":"sigmoid"
            }
          ]
        },
        {
          "value":"descending colon",
          "properties":{
            "tui":"T023"
          },
          "vocabulary_code":"32622004",
          "vocabulary":"SNOMED-CT",
          "vocabulary_version":"2016_03_01",
          "object_value_variants":[
            {
              "value":"descending"
            }
          ]
        },
        {
          "value":"splenic flexure",
          "properties":{
            "tui":"T023"
          },
          "vocabulary_code":"245428003",
          "vocabulary":"SNOMED-CT",
          "vocabulary_version":"2016_03_01",
          "object_value_variants":[
            {
              "value":"splenic"
            }
          ]
        },
        {
          "value":"transverse colon",
          "properties":{
            "tui":"T023"
          },
          "vocabulary_code":"485005",
          "vocabulary":"SNOMED-CT",
          "vocabulary_version":"2016_03_01",
          "object_value_variants":[
            {
              "value":"transverse"
            }
          ]
        },
        {
          "value":"hepatic flexure",
          "properties":{
            "tui":"T023"
          },
          "vocabulary_code":"48338005",
          "vocabulary":"SNOMED-CT",
          "vocabulary_version":"2016_03_01",
          "object_value_variants":[
            {
              "value":"hepatic"
            }
          ]
        },
        {
          "value":"ascending colon",
          "properties":{
            "tui":"T023"
          },
          "vocabulary_code":"9040008",
          "vocabulary":"SNOMED-CT",
          "vocabulary_version":"2016_03_01",
          "object_value_variants":[
            {
              "value":"ascending"
            }
          ]
        },
        {
          "value":"ileum",
          "properties":{
            "tui":"T023"
          },
          "vocabulary_code":"23153004",
          "vocabulary":"SNOMED-CT",
          "vocabulary_version":"2016_03_01",
          "object_value_variants":[
            {
              "value":"terminal ileum"
            }
          ]
        },
        {
          "value":"cecum",
          "properties":{
            "tui":"T023"
          },
          "vocabulary_code":"32713005",
          "vocabulary":"SNOMED-CT",
          "vocabulary_version":"2016_03_01",
          "object_value_variants":[
          ]
        },
        {
          "value":"appendix",
          "properties":{
            "tui":"T023"
          },
          "vocabulary_code":"66754008",
          "vocabulary":"SNOMED-CT",
          "vocabulary_version":"2016_03_01",
          "object_value_variants":[
            {
              "value":"appendiceal orifice"
            }
          ]
        },
        {
          "value":"ileocecal valve",
          "properties":{
            "tui":"T023"
          },
          "vocabulary_code":"",
          "vocabulary":"SNOMED-CT",
          "vocabulary_version":"2016_03_01",
          "object_value_variants":[
          ]
        },
        {
          "value":"anastomosis",
          "properties":{
            "tui":"T020"
          },
          "vocabulary_code":"41796003",
          "vocabulary":"SNOMED-CT",
          "vocabulary_version":"2016_03_01",
          "object_value_variants":[
          ]
        }
      ]
   }